{"last_node_id": 1, "last_link_id": 0, "nodes": [{"id": 1, "type": "\ud83d\udd78\ufe0f Adjust (jov)", "pos": [1950, 810], "size": {"0": 210, "1": 150}, "flags": {}, "order": 0, "mode": 0, "inputs": [{"name": "pixels", "type": "*", "link": null}], "outputs": [{"name": "image", "type": "IMAGE", "links": null, "shape": 3}, {"name": "mask", "type": "MASK", "links": null, "shape": 3}], "properties": {"Node name for S&R": "\ud83d\udd78\ufe0f Adjust (jov)"}, "widgets_values": ["BLUR", 1, 0, 0]}], "links": [], "groups": [], "config": {}, "extra": {}, "version": 0.4}