{"last_node_id":32,"last_link_id":47,"nodes":[{"id":8,"type":"Note","pos":{"0":580,"1":215},"size":{"0":210,"1":80},"flags":{"pinned":true},"order":0,"mode":0,"inputs":[],"outputs":[],"properties":{"text":""},"widgets_values":["ALPHA BLENDING WORKS FOR THE COLOR AS WELL AS MATTING IMAGES WITH EXISTING ALPHA CHANNELS."],"color":"#222","bgcolor":"#000","shape":1},{"id":21,"type":"PreviewImage","pos":{"0":800,"1":605},"size":{"0":220,"1":250},"flags":{},"order":5,"mode":0,"inputs":[{"name":"images","type":"IMAGE","link":46}],"outputs":[],"properties":{"Node name for S&R":"PreviewImage"},"widgets_values":[],"shape":1},{"id":25,"type":"CONSTANT (JOV) 🟪","pos":{"0":800,"1":215},"size":[220,125],"flags":{},"order":6,"mode":0,"inputs":[{"name":"👾","type":"*","link":47}],"outputs":[{"name":"🖼️","type":"IMAGE","links":[43],"shape":3,"slot_index":0},{"name":"🌈","type":"IMAGE","links":[41],"shape":3,"slot_index":1},{"name":"😷","type":"MASK","links":[42],"shape":3,"slot_index":2}],"properties":{"Node name for S&R":"CONSTANT (JOV) 🟪"},"widgets_values":[null,{"0":192,"1":128,"2":0,"3":255},"MATTE",[512,512],"LANCZOS4"],"color":"#1f991f","shape":1},{"id":26,"type":"CONSTANT (JOV) 🟪","pos":{"0":800,"1":425},"size":[220,125],"flags":{},"order":4,"mode":0,"inputs":[{"name":"👾","type":"*","link":29}],"outputs":[{"name":"🖼️","type":"IMAGE","links":[],"shape":3,"slot_index":0},{"name":"🌈","type":"IMAGE","links":[],"shape":3,"slot_index":1},{"name":"😷","type":"MASK","links":null,"shape":3}],"properties":{"Node name for S&R":"CONSTANT (JOV) 🟪"},"widgets_values":[null,{"0":192,"1":128,"2":0,"3":255},"MATTE",[512,512],"LANCZOS4"],"color":"#1f991f","shape":1},{"id":27,"type":"LoadImage","pos":{"0":-115,"1":310},"size":{"0":315,"1":315},"flags":{},"order":1,"mode":0,"inputs":[],"outputs":[{"name":"IMAGE","type":"IMAGE","links":[34],"shape":3,"slot_index":0},{"name":"MASK","type":"MASK","links":[35],"shape":3,"slot_index":1}],"properties":{"Node name for S&R":"LoadImage"},"widgets_values":["mask-a.png","image"]},{"id":31,"type":"MaskToImage","pos":{"0":1035,"1":715},"size":{"0":210,"1":26},"flags":{},"order":9,"mode":0,"inputs":[{"name":"mask","type":"MASK","link":42}],"outputs":[{"name":"IMAGE","type":"IMAGE","links":[38],"shape":3,"slot_index":0}],"properties":{"Node name for S&R":"MaskToImage"},"widgets_values":[]},{"id":22,"type":"QUEUE (JOV) 🗃","pos":{"0":580,"1":335},"size":[210,398],"flags":{},"order":2,"mode":0,"inputs":[],"outputs":[{"name":"🦄","type":"*","links":[29,46],"shape":3,"slot_index":0},{"name":"Q","type":"*","links":null,"shape":3},{"name":"CURRENT","type":"STRING","links":null,"shape":3},{"name":"INDEX","type":"INT","links":null,"shape":3},{"name":"TOTAL","type":"INT","links":null,"shape":3},{"name":"⚡","type":"BOOLEAN","links":null,"shape":3}],"properties":{"Node name for S&R":"QUEUE (JOV) 🗃"},"widgets_values":["C:/dev/ComfyUI/ComfyUI/custom_nodes/Jovimetrix/res/img/test-a.png",0,false,false,false,false,"[11 / 24]\nC:/dev/ComfyUI/ComfyUI/custom_nodes/Jovimetrix/res/img/mask-a.png",false,null,"[1 / 1]\nC:\\dev\\ComfyUI\\ComfyUI\\custom_nodes\\Jovimetrix\\res\\img\\test-a.png"],"color":"#0A0A0A","shape":1},{"id":30,"type":"JoinImageWithAlpha","pos":{"0":380,"1":60},"size":{"0":264.5999755859375,"1":46},"flags":{},"order":3,"mode":0,"inputs":[{"name":"image","type":"IMAGE","link":34},{"name":"alpha","type":"MASK","link":35}],"outputs":[{"name":"IMAGE","type":"IMAGE","links":[47],"shape":3,"slot_index":0}],"properties":{"Node name for S&R":"JoinImageWithAlpha"},"widgets_values":[]},{"id":32,"type":"PreviewImage","pos":{"0":1030,"1":-140},"size":[210,245],"flags":{},"order":7,"mode":0,"inputs":[{"name":"images","type":"IMAGE","link":43}],"outputs":[],"properties":{"Node name for S&R":"PreviewImage"},"widgets_values":[]},{"id":14,"type":"PreviewImage","pos":{"0":1030,"1":145},"size":{"0":220,"1":250},"flags":{},"order":8,"mode":0,"inputs":[{"name":"images","type":"IMAGE","link":41}],"outputs":[],"properties":{"Node name for S&R":"PreviewImage"},"widgets_values":[],"shape":1},{"id":10,"type":"PreviewImage","pos":{"0":1030,"1":425},"size":{"0":220,"1":250},"flags":{},"order":10,"mode":0,"inputs":[{"name":"images","type":"IMAGE","link":38}],"outputs":[],"properties":{"Node name for S&R":"PreviewImage"},"widgets_values":[],"shape":1}],"links":[[29,22,0,26,0,"*"],[34,27,0,30,0,"IMAGE"],[35,27,1,30,1,"MASK"],[38,31,0,10,0,"IMAGE"],[41,25,1,14,0,"IMAGE"],[42,25,2,31,0,"MASK"],[43,25,0,32,0,"IMAGE"],[46,22,0,21,0,"IMAGE"],[47,30,0,25,0,"*"]],"groups":[],"config":{},"extra":{"workspace_info":{"id":"f71a3c0d-c8f9-4a7c-aa9f-a8aec0e6b6d5","saveLock":false,"cloudID":null,"coverMediaPath":null},"ds":{"scale":1,"offset":[85.65819459675924,201.43042027052502]}},"version":0.4}